{"indexes":[{"v":{"$numberInt":"2"},"key":{"_id":{"$numberInt":"1"}},"name":"_id_"},{"v":{"$numberInt":"2"},"key":{"category":{"$numberInt":"1"},"publication_year":{"$numberInt":"1"}},"name":"category_1_publication_year_1"},{"v":{"$numberInt":"2"},"key":{"author":{"$numberInt":"1"}},"name":"author_1"},{"v":{"$numberInt":"2"},"key":{"_fts":"text","_ftsx":{"$numberInt":"1"}},"name":"description_text_title_text","weights":{"description":{"$numberInt":"1"},"title":{"$numberInt":"1"}},"default_language":"english","language_override":"language","textIndexVersion":{"$numberInt":"3"}}],"uuid":"ea3177b782fa4b76a51faa6c57df1170","collectionName":"books","type":"collection"}